moy_nalog/__init__.py
moy_nalog/constants.py
moy_nalog/exceptions.py
moy_nalog/http.py
moy_nalog/loggers.py
moy_nalog/methods/__init__.py
moy_nalog/methods/add_income.py
moy_nalog/methods/api.py
moy_nalog/methods/bonus.py
moy_nalog/methods/cancel_income.py
moy_nalog/methods/get_incomes.py
moy_nalog/methods/method.py
moy_nalog/methods/notifications.py
moy_nalog/methods/user.py
moy_nalog/moy_nalog.py
moy_nalog/types.py
moy_nalog-0.3.5.dist-info/LICENSE
moy_nalog-0.3.5.dist-info/METADATA
moy_nalog-0.3.5.dist-info/WHEEL
moy_nalog-0.3.5.dist-info/RECORD
