Metadata-Version: 2.1
Name: moy-nalog
Version: 0.3.5
Summary: Async Python API for lknpd.nalog.ru
Home-page: https://github.com/byBenPuls/moy_nalog
License: MIT
Keywords: api,finance,async,nalog,lknpd-nalog,moy-nalog,lknpd.nalog.ru,nalog.ru
Author: Ben Puls
Author-email: mail@benpuls.ru
Requires-Python: >=3.8
Classifier: License :: OSI Approved :: MIT License
Classifier: Programming Language :: Python :: 3
Classifier: Programming Language :: Python :: 3.8
Classifier: Programming Language :: Python :: 3.9
Classifier: Programming Language :: Python :: 3.10
Classifier: Programming Language :: Python :: 3.11
Classifier: Programming Language :: Python :: 3.12
Classifier: Programming Language :: Python :: 3.13
Requires-Dist: httpx (>=0.27.2,<0.28.0)
Project-URL: Documentation, https://moy-nalog.readthedocs.io/ru/latest/
Project-URL: Repository, https://github.com/byBenPuls/moy_nalog
